random_data_gen_joao/__init__.py
random_data_gen_joao/features/__init__.py
random_data_gen_joao/features/transactional_features.py
random_data_gen_joao-0.1.0.dist-info/WHEEL
random_data_gen_joao-0.1.0.dist-info/METADATA
random_data_gen_joao-0.1.0.dist-info/RECORD
