Metadata-Version: 2.1
Name: random-data-gen-joao
Version: 0.1.0
Summary: 
Author: João Paulo Nogueira
Author-email: joaonogueira@fisica.ufc.br
Requires-Python: >=3.9,<4.0
Classifier: Programming Language :: Python :: 3
Classifier: Programming Language :: Python :: 3.10
Classifier: Programming Language :: Python :: 3.9
Requires-Dist: numpy (>=1.22.1,<2.0.0)
Requires-Dist: pandas (>=1.4.0,<2.0.0)
